UAVision/__init__.py
UAVision/utils.py
UAVision/bin_edges/mcda_midbin_all.txt
UAVision/bin_edges/opcN2_binedges.txt
UAVision/bin_edges/opcN3_binedges.txt
UAVision/bin_edges/pops_binedges.txt
UAVision/bme/__init__.py
UAVision/bme/preprocess.py
UAVision/cpc/__init__.py
UAVision/cpc/preprocess.py
UAVision/mavic/__init__.py
UAVision/mavic/merge_sensor_data.py
UAVision/mavic/merge_wind_data.py
UAVision/mavic/preprocess.py
UAVision/mcda/__init__.py
UAVision/mcda/preprocess.py
UAVision/pops/__init__.py
UAVision/pops/preprocess.py
uavision-1.0.4.dist-info/licenses/LICENSE
uavision-1.0.4.dist-info/METADATA
uavision-1.0.4.dist-info/WHEEL
uavision-1.0.4.dist-info/top_level.txt
uavision-1.0.4.dist-info/RECORD
