Metadata-Version: 2.4
Name: UAVision
Version: 1.0.4
Summary: UAV instrument data processing
Author-email: VIET LE <viet.le@fmi.fi>
License: MIT License
Requires-Python: >=3.11
License-File: LICENSE
Requires-Dist: numpy
Requires-Dist: matplotlib
Requires-Dist: pandas
Dynamic: license-file
